intervaltree_rs-0.1.1.dist-info/METADATA
intervaltree_rs-0.1.1.dist-info/WHEEL
intervaltree_rs.pyi
intervaltree_rs/__init__.py
intervaltree_rs/__init__.pyi
intervaltree_rs/intervaltree_rs.abi3.so
intervaltree_rs/py.typed
intervaltree_rs-0.1.1.dist-info/RECORD
