Metadata-Version: 2.4
Name: intervaltree-rs
Version: 0.1.1
Classifier: Programming Language :: Python :: 3
Classifier: Programming Language :: Rust
Classifier: Programming Language :: Python :: Implementation :: CPython
Classifier: License :: OSI Approved :: MIT License
Classifier: Operating System :: OS Independent
Summary: Fast interval tree (Rust) with Python bindings
Author-email: Astarag Mohapatra <astarag2843@gmail.com>
License: MIT
Requires-Python: >=3.8
